setup.py
django_coreapi/__init__.py
django_coreapi/client.py
django_coreapi/mock.py
django_coreapi/renderers.py
django_coreapi/serializers.py
django_coreapi/transports.py
django_coreapi.egg-info/PKG-INFO
django_coreapi.egg-info/SOURCES.txt
django_coreapi.egg-info/dependency_links.txt
django_coreapi.egg-info/requires.txt
django_coreapi.egg-info/top_level.txt