Metadata-Version: 1.0
Name: django-coreapi
Version: 0.5.0
Summary: Core API helpers for Django and Django Rest Framework
Home-page: https://github.com/weargoggles/django-coreapi
Author: Pete Wildsmith
Author-email: pete@dabapps.com
License: BSD
Platform: UNKNOWN
